search4file/__init__.py
search4file/api/__init__.py
search4file/api/search_by_content.py
search4file/api/search_by_name.py
search4file/core/SearchByContent.py
search4file/core/SearchByName.py
search4file/core/__init__.py
search4file/core/SpecialFunc/SpecialExcel.py
search4file/core/SpecialFunc/__init__.py
search4file/lib/__init__.py
search4file/lib/test.py
search4file/lib/unhandle_file_type.py
search4file/lib/utils/__init__.py
search4file/lib/utils/except_utils.py
search4file/lib/utils/utils.py
tests/__init__.py
tests/test_search4file.py
search4file-0.1.15.dist-info/LICENSE
search4file-0.1.15.dist-info/METADATA
search4file-0.1.15.dist-info/WHEEL
search4file-0.1.15.dist-info/top_level.txt
search4file-0.1.15.dist-info/RECORD
