Metadata-Version: 2.1
Name: search4file
Version: 0.1.15
Summary: python for office
Home-page: https://github.com/CoderWanFeng/python-office
Author: CoderWanFeng
Author-email: 1957875073@qq.com
License: Apache-2.0 license
Project-URL: Bug Tracker, https://github.com/CoderWanFeng/search4file/issues
Project-URL: Documentation, https://github.com/CoderWanFeng/search4file/blob/main/README.md
Project-URL: Source Code, https://github.com/CoderWanFeng/search4file
Platform: any
Requires-Python: >=3.6
License-File: LICENSE
Requires-Dist: python-docx
Requires-Dist: xlrd
Requires-Dist: openpyxl
Requires-Dist: PyMuPDF
Requires-Dist: python-pptx
Requires-Dist: poprogress
Requires-Dist: pandas
